[
 {
  "author": "dkhaywood", 
  "date": "2007-09-27T21:35:52.650853Z", 
  "msg": [
   "NO IDE: fixes for #220 (server launch config); #314 (use -Dnakedobjects.fixture); #311 (force lower case for project names); also structured to make it easier to add new component installers in future; bumped manifest versions."
  ], 
  "revision_id": "1016655"
 }, 
 {
  "author": "dkhaywood", 
  "date": "2007-09-27T21:11:18.114534Z", 
  "msg": [
   "IDE icons: excluding .svn files."
  ], 
  "revision_id": "1016654"
 }, 
 {
  "author": "dkhaywood", 
  "date": "2007-09-27T21:10:27.331951Z", 
  "msg": [
   "NOF: bumping manifest version for CLI."
  ], 
  "revision_id": "1016653"
 }, 
 {
  "author": "dkhaywood", 
  "date": "2007-09-27T21:10:19.969484Z", 
  "msg": [
   "NOF: bumping manifest version for SQL OS."
  ], 
  "revision_id": "1016652"
 }, 
 {
  "author": "dkhaywood", 
  "date": "2007-09-27T21:10:13.559008Z", 
  "msg": [
   "NOF: bumping manifest version for cache OS."
  ], 
  "revision_id": "1016651"
 }
]