[
 {
  "author": "mor", 
  "date": "2011-01-29T05:41:42.482348Z", 
  "msg": [
   "Merged from trunk r1064954.", 
   "Log: Bug fix - Under the order items on Order Detail Page the Quantity Returned wasn't correct 'cause system is also adding up the quantities from a corresponding canceled return."
  ], 
  "revision_id": "1064955"
 }, 
 {
  "author": "mor", 
  "date": "2011-01-29T05:36:58.565277Z", 
  "msg": [
   "Bug fix - Under the order items on Order Detail Page the Quantity Returned wasn't correct 'cause system is also adding up the quantities from a corresponding canceled return."
  ], 
  "revision_id": "1064954"
 }, 
 {
  "author": "ashish", 
  "date": "2011-01-29T05:29:55.922949Z", 
  "msg": [
   "Bug fix. Returning communicationEventId from the service implementation which was defined OUT in service definition. Thanks Divesh!"
  ], 
  "revision_id": "1064953"
 }, 
 {
  "author": "oching", 
  "date": "2011-01-29T04:26:27.187791Z", 
  "msg": [
   "added Mark Struberg as contributor (MRM-1453)"
  ], 
  "revision_id": "1064952"
 }, 
 {
  "author": "zwoop", 
  "date": "2011-01-29T03:39:55.018669Z", 
  "msg": [
   "Update the directory layout"
  ], 
  "revision_id": "1064951"
 }
]