[
 {
  "author": "stsp", 
  "date": "2011-03-28T11:37:45.865310Z", 
  "msg": [
   "* subversion/libsvn_wc/wc-queries.sql", 
   "(STMT_SELECT_DELETION_INFO): Use AS keyword to make the fact that", 
   "'nodes_work' is an alias for 'nodes' more obvious."
  ], 
  "revision_id": "1086195"
 }, 
 {
  "author": "markt", 
  "date": "2011-03-28T11:35:06.887814Z", 
  "msg": [
   "Move allocate() calls outside sync blocks to address performance issues identified in Phil's testing"
  ], 
  "revision_id": "1086194"
 }, 
 {
  "author": "dblevins", 
  "date": "2011-03-28T11:30:52.904982Z", 
  "msg": [
   "Switch to interface version of AnnotationFinder"
  ], 
  "revision_id": "1086193"
 }, 
 {
  "author": "stsp", 
  "date": "2011-03-28T11:27:43.149172Z", 
  "msg": [
   "* subversion/libsvn_wc/wc_db.c", 
   "(has_local_mods): Don't use local variable 'have_row' where it's not", 
   "needed, tightening its scope.", 
   "Suggested by: gstein"
  ], 
  "revision_id": "1086192"
 }, 
 {
  "author": "dblevins", 
  "date": "2011-03-28T11:27:30.434769Z", 
  "msg": [
   "Copy of the interceptors example recast as a unit tests.  Seems this example picks up a lot of issues not covered in other tests"
  ], 
  "revision_id": "1086191"
 }
]