[
 {
  "author": "simonw", 
  "date": "2011-05-29T02:53:45.392832Z", 
  "msg": [
   "LUCENE-3147: remove @Override when inherit from Interface & fixed leaking file descriptors when exception is thrown through abort"
  ], 
  "revision_id": "1128810"
 }, 
 {
  "author": "joes", 
  "date": "2011-05-29T02:47:05.922669Z", 
  "msg": [
   "bring inline with nix non-setting of DEFS"
  ], 
  "revision_id": "1128809"
 }, 
 {
  "author": "hansbak", 
  "date": "2011-05-29T02:43:01.172039Z", 
  "msg": [
   "show new catalogbutton on the find screen, but not on the new catalog screen"
  ], 
  "revision_id": "1128808"
 }, 
 {
  "author": "hansbak", 
  "date": "2011-05-29T02:32:10.470975Z", 
  "msg": [
   "show new catalogbutton on the find screen"
  ], 
  "revision_id": "1128807"
 }, 
 {
  "author": "joes", 
  "date": "2011-05-29T02:29:47.928324Z", 
  "msg": [
   "oops. these are separate args"
  ], 
  "revision_id": "1128806"
 }
]