[
 {
  "author": "dion", 
  "date": "2003-10-08T17:07:44.000000Z", 
  "msg": [
   "Fix typo giving aslak credit back :-)"
  ], 
  "revision_id": "114179"
 }, 
 {
  "author": "dion", 
  "date": "2003-10-08T16:56:34.000000Z", 
  "msg": [
   "Apply MAVEN-852"
  ], 
  "revision_id": "114178"
 }, 
 {
  "author": "dion", 
  "date": "2003-10-08T16:49:14.000000Z", 
  "msg": [
   "Apply MAVEN-850"
  ], 
  "revision_id": "114177"
 }, 
 {
  "author": "dion", 
  "date": "2003-10-08T16:41:59.000000Z", 
  "msg": [
   "Apply MAVEN-890"
  ], 
  "revision_id": "114176"
 }, 
 {
  "author": "dion", 
  "date": "2003-10-08T16:38:11.000000Z", 
  "msg": [
   "Fix for MAVEN-888"
  ], 
  "revision_id": "114175"
 }
]