[
 {
  "author": "mturk", 
  "date": "2011-10-26T13:26:42.263224Z", 
  "msg": [
   "Move lxc code into os/linux"
  ], 
  "revision_id": "1189200"
 }, 
 {
  "author": "lahiru", 
  "date": "2011-10-26T13:26:25.773984Z", 
  "msg": [
   "enabling test cases in ws-messenger."
  ], 
  "revision_id": "1189199"
 }, 
 {
  "author": "mgrigorov", 
  "date": "2011-10-26T13:26:08.745780Z", 
  "msg": [
   "WICKET-4177 Use Clirr Maven Plugin to keep Wicket API backward compatible"
  ], 
  "revision_id": "1189198"
 }, 
 {
  "author": "ggregory", 
  "date": "2011-10-26T13:24:59.125647Z", 
  "msg": [
   "Remove unused imports."
  ], 
  "revision_id": "1189197"
 }, 
 {
  "author": "ggregory", 
  "date": "2011-10-26T13:23:21.351653Z", 
  "msg": [
   "Fix typo in // comment."
  ], 
  "revision_id": "1189196"
 }
]