[
 {
  "author": "szetszwo", 
  "date": "2011-11-03T22:35:58.007705Z", 
  "msg": [
   "HDFS-2527. WebHdfs: remove the use of \"Range\" header in Open; use ugi username if renewer parameter is null in GetDelegationToken; response OK when setting replication for non-files; rename GETFILEBLOCKLOCATIONS to GET_BLOCK_LOCATIONS and state that it is a private unstable API; replace isDirectory and isSymlink with enum {FILE, DIRECTORY, SYMLINK} in HdfsFileStatus JSON object."
  ], 
  "revision_id": "1197330"
 }, 
 {
  "author": "szetszwo", 
  "date": "2011-11-03T22:34:47.974435Z", 
  "msg": [
   "HDFS-2527. WebHdfs: remove the use of \"Range\" header in Open; use ugi username if renewer parameter is null in GetDelegationToken; response OK when setting replication for non-files; rename GETFILEBLOCKLOCATIONS to GET_BLOCK_LOCATIONS and state that it is a private unstable API; replace isDirectory and isSymlink with enum {FILE, DIRECTORY, SYMLINK} in HdfsFileStatus JSON object."
  ], 
  "revision_id": "1197329"
 }, 
 {
  "author": "jens", 
  "date": "2011-11-03T22:25:24.163942Z", 
  "msg": [
   "Improve MoReq type definitions"
  ], 
  "revision_id": "1197328"
 }, 
 {
  "author": "gnodet", 
  "date": "2011-11-03T22:11:12.984163Z", 
  "msg": [
   "Add karaf download box sources"
  ], 
  "revision_id": "1197327"
 }, 
 {
  "author": "astitcher", 
  "date": "2011-11-03T22:11:11.550931Z", 
  "msg": [
   "QPID-3464: Build Improvements (autotools) [inspired by  Jan-Marek Glogowski]", 
   "- Simplified the python binding build", 
   "QPID-3458: Install compiled _cqpid.so for SWIG python bindings in site-packages directory", 
   "- Put the generated .pyc/.pyo and native .so in the correct place in the", 
   "install tree"
  ], 
  "revision_id": "1197326"
 }
]