[
 {
  "author": "dashorst", 
  "date": "2011-11-16T17:58:36.492156Z", 
  "msg": [
   "Set the compiler version to use and generate java 6"
  ], 
  "revision_id": "1202810"
 }, 
 {
  "author": "pburba", 
  "date": "2011-11-16T17:56:18.997411Z", 
  "msg": [
   "* STATUS: Nominate r1202807."
  ], 
  "revision_id": "1202809"
 }, 
 {
  "author": "sebb", 
  "date": "2011-11-16T17:53:39.038290Z", 
  "msg": [
   "Unused import"
  ], 
  "revision_id": "1202808"
 }, 
 {
  "author": "pburba", 
  "date": "2011-11-16T17:50:22.492267Z", 
  "msg": [
   "Fix a potential segfault during a merge.", 
   "Found by: steveking", 
   "See http://svn.haxx.se/dev/archive-2011-11/0261.shtml", 
   "* subversion/libsvn_client/merge.c", 
   "(merge_props_changed): Account for the fact that the", 
   "svn_wc_get_pristine_props API may return NULL pristine properties."
  ], 
  "revision_id": "1202807"
 }, 
 {
  "author": "rgardler", 
  "date": "2011-11-16T17:48:07.285001Z", 
  "msg": [
   "improve layout on smaller screens (thanks to Steve Lee fixes wookie-291"
  ], 
  "revision_id": "1202806"
 }
]