[
 {
  "author": "olegk", 
  "date": "2011-12-21T16:26:37.700240Z", 
  "msg": [
   "Javadoc updates"
  ], 
  "revision_id": "1221788"
 }, 
 {
  "author": "davidb", 
  "date": "2011-12-21T16:25:54.363517Z", 
  "msg": [
   "Add support for FrameworkMBean.refreshBundlesAndWait()"
  ], 
  "revision_id": "1221787"
 }, 
 {
  "author": "sergeyb", 
  "date": "2011-12-21T16:24:46.565471Z", 
  "msg": [
   "[DOSGI-75] Using CXF LogUtils to obtain a logger"
  ], 
  "revision_id": "1221786"
 }, 
 {
  "author": "pamarcelot", 
  "date": "2011-12-21T16:20:48.324743Z", 
  "msg": [
   "Fixed javadoc."
  ], 
  "revision_id": "1221785"
 }, 
 {
  "author": "heshan", 
  "date": "2011-12-21T16:18:25.266054Z", 
  "msg": [
   "Adding workflow samples tutorial to the index page AIRAVATA-247"
  ], 
  "revision_id": "1221784"
 }
]