[
 {
  "author": "veithen", 
  "date": "2012-01-14T09:13:09.161658Z", 
  "msg": [
   "Updated to latest mime4j release."
  ], 
  "revision_id": "1231468"
 }, 
 {
  "author": "sagara", 
  "date": "2012-01-14T09:07:40.732398Z", 
  "msg": [
   "Merged r1231465 to the 1.5 branch."
  ], 
  "revision_id": "1231467"
 }, 
 {
  "author": "sagara", 
  "date": "2012-01-14T09:05:21.517563Z", 
  "msg": [
   "Merged r1231465 to the 1.6 branch."
  ], 
  "revision_id": "1231466"
 }, 
 {
  "author": "sagara", 
  "date": "2012-01-14T08:55:06.153857Z", 
  "msg": [
   "Applied patch for AXIS2-4240."
  ], 
  "revision_id": "1231465"
 }, 
 {
  "author": "spamassassin_role", 
  "date": "2012-01-14T08:51:02.817586Z", 
  "msg": [
   "promotions validated"
  ], 
  "revision_id": "1231464"
 }
]