[
 {
  "author": "abayer", 
  "date": "2012-08-12T18:46:54.833116Z", 
  "msg": [
   "WHIRR-616. Allow multiple YARN node managers to run on a cluster. Contributed by Godwin Babu."
  ], 
  "revision_id": "1372173"
 }, 
 {
  "author": "robbie", 
  "date": "2012-08-12T18:46:21.286620Z", 
  "msg": [
   "QPID-4111: fix issue in the docbook markup to get the PDF generation working again"
  ], 
  "revision_id": "1372172"
 }, 
 {
  "author": "rmuir", 
  "date": "2012-08-12T18:45:46.649998Z", 
  "msg": [
   "revisit payloads API in DocsAndPositionsEnum"
  ], 
  "revision_id": "1372171"
 }, 
 {
  "author": "abayer", 
  "date": "2012-08-12T18:45:10.083846Z", 
  "msg": [
   "WHIRR-616. Allow multiple YARN node managers on a cluster. Contributed by Godwin Babu."
  ], 
  "revision_id": "1372170"
 }, 
 {
  "author": "lewismc", 
  "date": "2012-08-12T18:38:46.051237Z", 
  "msg": [
   "trivial commit to correct test artifact config"
  ], 
  "revision_id": "1372169"
 }
]