[
 {
  "author": "olamy", 
  "date": "2012-08-24T14:27:05.486101Z", 
  "msg": [
   "change lucene query to treat user input as scored value and version as exact value"
  ], 
  "revision_id": "1376938"
 }, 
 {
  "author": "szetszwo", 
  "date": "2012-08-24T14:24:59.220092Z", 
  "msg": [
   "svn merge -c 1376928 from trunk for HDFS-3177. Update DFSClient and DataXceiver to handle different checkum types in file checksum computation."
  ], 
  "revision_id": "1376937"
 }, 
 {
  "author": "dpfister", 
  "date": "2012-08-24T14:22:21.186490Z", 
  "msg": [
   "Add configuration for logger with INFO default level"
  ], 
  "revision_id": "1376936"
 }, 
 {
  "author": "ggregory", 
  "date": "2012-08-24T14:21:54.074499Z", 
  "msg": [
   "- Update commons-io for tests to 2.4 from 2.2.", 
   "- Update findbugs-maven-plugin to 2.5.2 from 2.4.", 
   "- Update clirr-maven-plugin to 2.4 from 2.3."
  ], 
  "revision_id": "1376935"
 }, 
 {
  "author": "gtully", 
  "date": "2012-08-24T14:21:22.929298Z", 
  "msg": [
   "https://issues.apache.org/jira/browse/AMQ-3557 - Performance of consumption with JDBC persistance and Microsoft SQL Server. Fix up default value for maxRows to allign with default page size. Use a large maxPageSize via destination policy for durable subs that have sparse selectors. Same as queues with sparse selectors"
  ], 
  "revision_id": "1376934"
 }
]