[
 {
  "author": "bimargulies", 
  "date": "2012-08-31T17:08:26.898025Z", 
  "msg": [
   "MSHADE-124: Need better plan for getting dependency-reduced-pom.xml out of basedir", 
   "o add integration test for new unique name generator."
  ], 
  "revision_id": "1379508"
 }, 
 {
  "author": "cwiklik", 
  "date": "2012-08-31T17:05:08.437981Z", 
  "msg": [
   "UIMA-2436 fixed a bug that produced two sets of uima core jars in the lib dir."
  ], 
  "revision_id": "1379507"
 }, 
 {
  "author": "suresh", 
  "date": "2012-08-31T17:01:25.409283Z", 
  "msg": [
   "HADOOP-8684. Deadlock between WritableComparator and WritableComparable. Contributed by Jing Zhao"
  ], 
  "revision_id": "1379506"
 }, 
 {
  "author": "rhillegas", 
  "date": "2012-08-31T16:55:20.429587Z", 
  "msg": [
   "DERBY-672: Add support for DISTINCT user defined aggregates in the SELECT list."
  ], 
  "revision_id": "1379505"
 }, 
 {
  "author": "olamy", 
  "date": "2012-08-31T16:55:13.702203Z", 
  "msg": [
   "Apache Redback Core site deployment"
  ], 
  "revision_id": "1379504"
 }
]