[
 {
  "author": "jbonofre", 
  "date": "2012-09-19T19:11:38.884693Z", 
  "msg": [
   "Use same Maven XSD in all POM"
  ], 
  "revision_id": "1387708"
 }, 
 {
  "author": "jbonofre", 
  "date": "2012-09-19T19:06:45.808288Z", 
  "msg": [
   "Use same Maven XSD in all POM"
  ], 
  "revision_id": "1387707"
 }, 
 {
  "author": "todd", 
  "date": "2012-09-19T18:57:11.206719Z", 
  "msg": [
   "HDFS-3955. QJM: Make acceptRecovery() atomic. Contributed by Todd Lipcon."
  ], 
  "revision_id": "1387706"
 }, 
 {
  "author": "lahiru", 
  "date": "2012-09-19T18:53:14.794965Z", 
  "msg": [], 
  "revision_id": "1387705"
 }, 
 {
  "author": "todd", 
  "date": "2012-09-19T18:52:15.348380Z", 
  "msg": [
   "HDFS-3950. QJM: misc TODO cleanup, improved log messages, etc. Contributed by Todd Lipcon."
  ], 
  "revision_id": "1387704"
 }
]