[
 {
  "author": "martinc", 
  "date": "2002-10-07T00:56:12.000000Z", 
  "msg": [
   "Links to Validator now go to the Validator web site, rather than viewcvs."
  ], 
  "revision_id": "142309"
 }, 
 {
  "author": "bayard", 
  "date": "2002-10-04T04:18:37.000000Z", 
  "msg": [
   "Updated webpage to mention new release."
  ], 
  "revision_id": "142308"
 }, 
 {
  "author": "dion", 
  "date": "2002-10-03T23:36:56.000000Z", 
  "msg": [
   "Shared jakarta logo across projects"
  ], 
  "revision_id": "142307"
 }, 
 {
  "author": "dion", 
  "date": "2002-10-03T09:18:44.000000Z", 
  "msg": [
   "Fix web site directory"
  ], 
  "revision_id": "142306"
 }, 
 {
  "author": "rdonkin", 
  "date": "2002-09-27T21:05:13.000000Z", 
  "msg": [
   "Removed section containing pending proposals. This was hopelessly out of date and is in pratice unmaintainable. The system which seems to have emerged is that projects tend to serve a probation in the sandbox and are then promoted (or not) so this section wasn't very useful anyway."
  ], 
  "revision_id": "142305"
 }
]