[
 {
  "author": "proyal", 
  "date": "2002-07-16T17:54:13.000000Z", 
  "msg": [
   "Added config option to specify a path to serialize", 
   "configurations out to for debugging."
  ], 
  "revision_id": "14244"
 }, 
 {
  "author": "crafterm", 
  "date": "2002-07-16T12:35:45.000000Z", 
  "msg": [
   "Added catch for ClassCastException which might occur if a Serviceable", 
   "component is looked up inside of a ComponentManager, but does not", 
   "implement Component.", 
   "The exception is explicitly rethrown as a ServiceException to alert the", 
   "caller about the problem (rather than continue as a RuntimeException)."
  ], 
  "revision_id": "14243"
 }, 
 {
  "author": "hammant", 
  "date": "2002-07-15T20:40:51.000000Z", 
  "msg": [
   "MX4J compatible with Default JMX in terms of port setting in Kernel config XML"
  ], 
  "revision_id": "14242"
 }, 
 {
  "author": "bloritsch", 
  "date": "2002-07-15T20:02:16.000000Z", 
  "msg": [
   "apply fix for missing spaces in NamespacedSAXConfigurationHandler.java"
  ], 
  "revision_id": "14241"
 }, 
 {
  "author": "proyal", 
  "date": "2002-07-15T16:18:31.000000Z", 
  "msg": [
   "Fixed Checkstyle errors + moved inner class to be package level"
  ], 
  "revision_id": "14240"
 }
]