[
 {
  "author": "jacques", 
  "date": "2013-06-12T21:09:03.044789Z", 
  "msg": [
   "CMS commit to drill by jacques"
  ], 
  "revision_id": "1492428"
 }, 
 {
  "author": "swagle", 
  "date": "2013-06-12T21:04:44.153175Z", 
  "msg": [
   "AMBARI-2369. B6 setup stops on Postgresql start on SLES11. (swagle)"
  ], 
  "revision_id": "1492427"
 }, 
 {
  "author": "swagle", 
  "date": "2013-06-12T20:59:03.956741Z", 
  "msg": [
   "AMBARI-2369. B6 setup stops on Postgresql start on SLES11. (swagle)"
  ], 
  "revision_id": "1492426"
 }, 
 {
  "author": "dkulp", 
  "date": "2013-06-12T20:57:59.977299Z", 
  "msg": [
   "[CXF-5071] Make sure configs that set the SSLSocketFactory delegate down to URLConnection based impl"
  ], 
  "revision_id": "1492425"
 }, 
 {
  "author": "ssc", 
  "date": "2013-06-12T20:57:00.064277Z", 
  "msg": [
   "MAHOUT-1258 Another shot at findbugs and checkstyle"
  ], 
  "revision_id": "1492424"
 }
]