[
 {
  "author": "justin", 
  "date": "2013-06-27T19:28:59.782524Z", 
  "msg": [
   "SLING-2937 - using Long.valueOf() in getLong() to ensure correct parsing"
  ], 
  "revision_id": "1497518"
 }, 
 {
  "author": "dkulp", 
  "date": "2013-06-27T19:28:48.093297Z", 
  "msg": [
   "Blocking revisions 1496566,1496631 via  git from", 
   "https://svn.apache.org/repos/asf/cxf/trunk"
  ], 
  "revision_id": "1497517"
 }, 
 {
  "author": "dkulp", 
  "date": "2013-06-27T19:28:46.124008Z", 
  "msg": [
   "Recording revisions 1497066,1497481 via  git from", 
   "https://svn.apache.org/repos/asf/cxf/trunk"
  ], 
  "revision_id": "1497516"
 }, 
 {
  "author": "dkulp", 
  "date": "2013-06-27T19:28:41.240879Z", 
  "msg": [
   "Merged revisions 1497481 via  git cherry-pick from", 
   "https://svn.apache.org/repos/asf/cxf/trunk", 
   "........", 
   "r1497481 | dkulp | 2013-06-27 14:04:21 -0400 (Thu, 27 Jun 2013) | 2 lines", 
   "[CXF-5099] Fix problem of optional extensions not being truely optional", 
   "........"
  ], 
  "revision_id": "1497515"
 }, 
 {
  "author": "dkulp", 
  "date": "2013-06-27T19:28:36.748362Z", 
  "msg": [
   "Merged revisions 1497066 via  git cherry-pick from", 
   "https://svn.apache.org/repos/asf/cxf/trunk", 
   "........", 
   "r1497066 | dkulp | 2013-06-26 16:07:37 -0400 (Wed, 26 Jun 2013) | 2 lines", 
   "Remove some unneeded stuff from the src distro that just makes it bigger", 
   "........"
  ], 
  "revision_id": "1497514"
 }
]