[
 {
  "author": "fchrist", 
  "date": "2013-07-23T20:11:56.173994Z", 
  "msg": [
   "STANBOL-1139 Adding missing license headers"
  ], 
  "revision_id": "1506253"
 }, 
 {
  "author": "cwiklik", 
  "date": "2013-07-23T20:10:42.338472Z", 
  "msg": [
   "UIMA-3101 closed Reader when done processing stream"
  ], 
  "revision_id": "1506252"
 }, 
 {
  "author": "cwiklik", 
  "date": "2013-07-23T20:08:33.961445Z", 
  "msg": [
   "UIMA-3101 closed Reader when done processing stream"
  ], 
  "revision_id": "1506251"
 }, 
 {
  "author": "cwiklik", 
  "date": "2013-07-23T20:01:35.374718Z", 
  "msg": [
   "UIMA-3101 Close stream after use"
  ], 
  "revision_id": "1506250"
 }, 
 {
  "author": "cwiklik", 
  "date": "2013-07-23T19:58:09.598584Z", 
  "msg": [
   "UIMA-3101 Closed input streams after use"
  ], 
  "revision_id": "1506249"
 }
]