[
 {
  "author": "abroekhuis", 
  "date": "2013-10-02T09:08:43.326230Z", 
  "msg": [
   "CELIX-58: Added BUNDLE_UNKNOWN state for easier handling of the bundle state"
  ], 
  "revision_id": "1528388"
 }, 
 {
  "author": "abroekhuis", 
  "date": "2013-10-02T09:08:14.102461Z", 
  "msg": [
   "CELIX-56, CELIX-57: Fixed several small code issues"
  ], 
  "revision_id": "1528387"
 }, 
 {
  "author": "abroekhuis", 
  "date": "2013-10-02T09:07:09.241231Z", 
  "msg": [
   "CELIX-56: Renamed utils functions to follow the correct style"
  ], 
  "revision_id": "1528386"
 }, 
 {
  "author": "abroekhuis", 
  "date": "2013-10-02T09:05:31.195102Z", 
  "msg": [
   "CELIX-55: Added tests, removed old unused files (test frameworks etc)."
  ], 
  "revision_id": "1528385"
 }, 
 {
  "author": "markt", 
  "date": "2013-10-02T09:03:49.599902Z", 
  "msg": [
   "Swallow exception when writing to a closed client"
  ], 
  "revision_id": "1528384"
 }
]