[
 {
  "author": "jbonofre", 
  "date": "2014-09-09T11:06:55.593407Z", 
  "msg": [
   "[maven-release-plugin] prepare release org.apache.servicemix.bundles.spring-context-support-3.2.11.RELEASE_1"
  ], 
  "revision_id": "1623753"
 }, 
 {
  "author": "noble", 
  "date": "2014-09-09T11:03:37.490173Z", 
  "msg": [
   "SOLR-6457"
  ], 
  "revision_id": "1623752"
 }, 
 {
  "author": "jbonofre", 
  "date": "2014-09-09T11:01:19.233871Z", 
  "msg": [
   "[maven-release-plugin] prepare for next development iteration"
  ], 
  "revision_id": "1623751"
 }, 
 {
  "author": "jbonofre", 
  "date": "2014-09-09T11:01:15.138161Z", 
  "msg": [
   "[maven-release-plugin]  copy for tag org.apache.servicemix.bundles.spring-context-3.2.11.RELEASE_1"
  ], 
  "revision_id": "1623750"
 }, 
 {
  "author": "jbonofre", 
  "date": "2014-09-09T11:01:09.434305Z", 
  "msg": [
   "[maven-release-plugin] prepare release org.apache.servicemix.bundles.spring-context-3.2.11.RELEASE_1"
  ], 
  "revision_id": "1623749"
 }
]