[
 {
  "author": "sathwik", 
  "date": "2014-11-17T07:12:16.251316Z", 
  "msg": [
   "list items"
  ], 
  "revision_id": "1640073"
 }, 
 {
  "author": "fmeschbe", 
  "date": "2014-11-17T07:08:29.803583Z", 
  "msg": [
   "Ignore Eclipse .settings folder"
  ], 
  "revision_id": "1640072"
 }, 
 {
  "author": "sathwik", 
  "date": "2014-11-17T07:05:46.588087Z", 
  "msg": [
   "Draft integrating Bitonix TM with Tomcat and ODE"
  ], 
  "revision_id": "1640071"
 }, 
 {
  "author": "michim", 
  "date": "2014-11-17T06:48:15.416157Z", 
  "msg": [
   "ZOOKEEPER-2079 Stop daemon with \"kill\" rather than \"kill -9\" (Guillaume ALAUX via michim)"
  ], 
  "revision_id": "1640070"
 }, 
 {
  "author": "michim", 
  "date": "2014-11-17T06:47:25.003688Z", 
  "msg": [
   "ZOOKEEPER-2079 Stop daemon with \"kill\" rather than \"kill -9\" (Guillaume ALAUX via michim)"
  ], 
  "revision_id": "1640069"
 }
]