[
 {
  "author": "desruisseaux", 
  "date": "2015-03-20T11:52:25.371462Z", 
  "msg": [
   "Matrix: added a test case for MatrixSIS.concatenate(...), and documentation fixes."
  ], 
  "revision_id": "1667988"
 }, 
 {
  "author": "humbedooh", 
  "date": "2015-03-20T11:26:36.487629Z", 
  "msg": [
   "Start adding some election viewing stuff.", 
   "See http://stv.website/election.html?foo for an example"
  ], 
  "revision_id": "1667987"
 }, 
 {
  "author": "julianfoad", 
  "date": "2015-03-20T11:24:51.885340Z", 
  "msg": [
   "* STATUS: Vote for r1667941 group (bump copyright year)."
  ], 
  "revision_id": "1667986"
 }, 
 {
  "author": "julianfoad", 
  "date": "2015-03-20T11:24:19.108486Z", 
  "msg": [
   "* STATUS: Vote for r1667941 group (bump copyright year), r1597884 (swig-rb", 
   "test config fix)."
  ], 
  "revision_id": "1667985"
 }, 
 {
  "author": "mdisabatino", 
  "date": "2015-03-20T11:23:53.573175Z", 
  "msg": [
   "Staging site for release"
  ], 
  "revision_id": "1667984"
 }
]