[
 {
  "author": "areek", 
  "date": "2015-03-27T22:37:49.018735Z", 
  "msg": [
   "LUCENE-6339: Added Near-real time Document Suggester via custom postings format"
  ], 
  "revision_id": "1669698"
 }, 
 {
  "author": "andyetitmoves", 
  "date": "2015-03-27T22:33:54.383007Z", 
  "msg": [
   "SOLR-7309: Make bin/solr, bin/post work when Solr installation directory contains spaces"
  ], 
  "revision_id": "1669697"
 }, 
 {
  "author": "humbedooh", 
  "date": "2015-03-27T22:31:08.780200Z", 
  "msg": [
   "props (EOL: native)"
  ], 
  "revision_id": "1669696"
 }, 
 {
  "author": "humbedooh", 
  "date": "2015-03-27T22:14:28.575567Z", 
  "msg": [
   "Add a very quick guide and a standalone http server for testing purposes."
  ], 
  "revision_id": "1669695"
 }, 
 {
  "author": "humbedooh", 
  "date": "2015-03-27T22:09:37.225220Z", 
  "msg": [
   "buggo"
  ], 
  "revision_id": "1669694"
 }
]