[
 {
  "author": "juergen", 
  "date": "2002-05-22T07:37:46.000000Z", 
  "msg": [
   "Replaced usage of the org.w3c.dom classes by JDOM.", 
   "(ralf)"
  ], 
  "revision_id": "204659"
 }, 
 {
  "author": "juergen", 
  "date": "2002-05-22T07:36:40.000000Z", 
  "msg": [
   "Just a minor refactoring so it may be reused as a super class of PropPatchProperties.", 
   "(ralf)"
  ], 
  "revision_id": "204658"
 }, 
 {
  "author": "pnever", 
  "date": "2002-05-21T09:04:40.000000Z", 
  "msg": [
   "Fixed typos"
  ], 
  "revision_id": "204657"
 }, 
 {
  "author": "pnever", 
  "date": "2002-05-21T09:04:31.000000Z", 
  "msg": [
   "Catch NPE if StandardLivePropertiesClass parameter missing"
  ], 
  "revision_id": "204656"
 }, 
 {
  "author": "pnever", 
  "date": "2002-05-21T09:04:17.000000Z", 
  "msg": [
   "Catch NPE if UriRedirectorClass parameter missing"
  ], 
  "revision_id": "204655"
 }
]