[
 {
  "author": "sanjaya", 
  "date": "2003-12-24T11:30:22.000000Z", 
  "msg": [
   "fixed buggy code in  the perprocess method to get the TargetEnpointURI", 
   "correctly"
  ], 
  "revision_id": "250159"
 }, 
 {
  "author": "sanjaya", 
  "date": "2003-12-24T11:28:53.000000Z", 
  "msg": [
   "fixed getClassNameFromParamInfoConsideringArrays method to correctly", 
   "generate simple types."
  ], 
  "revision_id": "250158"
 }, 
 {
  "author": "sanjaya", 
  "date": "2003-12-24T07:07:01.000000Z", 
  "msg": [
   "corrected the default targetendpoint URL"
  ], 
  "revision_id": "250157"
 }, 
 {
  "author": "dims", 
  "date": "2003-12-23T14:46:56.000000Z", 
  "msg": [
   "- build the zip file in dist and srcdist", 
   "- ensure that the applet code is in WEB-INF/classes"
  ], 
  "revision_id": "250156"
 }, 
 {
  "author": "ias", 
  "date": "2003-12-23T11:38:44.000000Z", 
  "msg": [
   "Updated plan with status and testing"
  ], 
  "revision_id": "250155"
 }
]