[
 {
  "author": "damitha", 
  "date": "2004-04-05T07:02:08.000000Z", 
  "msg": [
   "Made a small change which prevented this sample from building."
  ], 
  "revision_id": "250629"
 }, 
 {
  "author": "susantha", 
  "date": "2004-04-04T12:59:14.000000Z", 
  "msg": [
   "1. Some fixes of base64Binary/HexBinary functionality", 
   "2. Adding AxisAdmin.wsdl", 
   "3. Correcting minor problems in RPC style code generation in WSDL2Ws tool (missing URI in Soap Method etc)", 
   "4. Uncommenting some code in interop client samples and minor corrections"
  ], 
  "revision_id": "250628"
 }, 
 {
  "author": "susantha", 
  "date": "2004-04-04T12:52:30.000000Z", 
  "msg": [
   "Adding project files for AdminClient and server"
  ], 
  "revision_id": "250627"
 }, 
 {
  "author": "dims", 
  "date": "2004-04-03T09:45:36.000000Z", 
  "msg": [
   "Fix for AXIS-1282 - Trim whitespace when reading wsdl file location from wsdd", 
   "from Sam Meder"
  ], 
  "revision_id": "250626"
 }, 
 {
  "author": "dims", 
  "date": "2004-04-03T09:43:19.000000Z", 
  "msg": [
   "Fix for AXIS-814 - URI does not over-ride hashcode()", 
   "reported by Sam Meder"
  ], 
  "revision_id": "250625"
 }
]