[
 {
  "author": "susantha", 
  "date": "2004-06-11T05:01:29.000000Z", 
  "msg": [
   "Added support for generating code for xsd:any in document literal style wsdls."
  ], 
  "revision_id": "251199"
 }, 
 {
  "author": "hemapani", 
  "date": "2004-06-10T11:35:19.000000Z", 
  "msg": [
   "replace misspelled *Genarator* with the Generator"
  ], 
  "revision_id": "251198"
 }, 
 {
  "author": "hemapani", 
  "date": "2004-06-10T11:33:12.000000Z", 
  "msg": [
   "update the packager to able to add jar files and create new jar file having all files in the both jarfiles"
  ], 
  "revision_id": "251197"
 }, 
 {
  "author": "damitha", 
  "date": "2004-06-10T11:31:27.000000Z", 
  "msg": [
   "PR:", 
   "Obtained from:", 
   "Submitted by:", 
   "Reviewed by:"
  ], 
  "revision_id": "251196"
 }, 
 {
  "author": "damitha", 
  "date": "2004-06-10T11:24:26.000000Z", 
  "msg": [
   "*** empty log message ***"
  ], 
  "revision_id": "251195"
 }
]