[
 {
  "author": "dims", 
  "date": "2005-01-19T21:04:22.000000Z", 
  "msg": [
   "Reduce the # of places Default***TypeMappingImpl's are created.", 
   "Note:", 
   "- Am not done cleaning up yet :)"
  ], 
  "revision_id": "260399"
 }, 
 {
  "author": "dicka", 
  "date": "2005-01-19T15:43:48.000000Z", 
  "msg": [
   "Remove compilation warning on Linux relating to #PRAGMA, which should only be in effect on Windows.", 
   "PR: AXISCPP-155", 
   "Submitted by: Adrian Dick"
  ], 
  "revision_id": "260398"
 }, 
 {
  "author": "dicka", 
  "date": "2005-01-19T15:22:33.000000Z", 
  "msg": [
   "Fix memory leaks in XSD objects.", 
   "PR: AXISCPP-384", 
   "Submitted by: Adrian Dick"
  ], 
  "revision_id": "260397"
 }, 
 {
  "author": "samisa", 
  "date": "2005-01-19T12:00:39.000000Z", 
  "msg": [
   "Clean up memory allocated for Stub"
  ], 
  "revision_id": "260396"
 }, 
 {
  "author": "whitlock", 
  "date": "2005-01-19T10:55:43.000000Z", 
  "msg": [
   "More C bindings: add Stub"
  ], 
  "revision_id": "260395"
 }
]