[
 {
  "author": "billbarker", 
  "date": "2002-11-23T09:04:16.000000Z", 
  "msg": [
   "Last one wasn't quite right.  At the momement, all SSL attributes are grabbed for a request for any.  Thus checking the 'key' isn't good enough."
  ], 
  "revision_id": "298174"
 }, 
 {
  "author": "billbarker", 
  "date": "2002-11-23T08:38:23.000000Z", 
  "msg": [
   "Return to Servlet-Spec 2.2 compliance.", 
   "Revert to the brain-dead 2.2 spec.  We are only allowed to send the top level cert in 2.2 land, so don't send the full array."
  ], 
  "revision_id": "298173"
 }, 
 {
  "author": "hgomez", 
  "date": "2002-11-23T06:34:47.000000Z", 
  "msg": [
   "Fix null getRemoteHost.", 
   "Lasy extraction of ssl certs to speed up jk/ajp13 when under SSL"
  ], 
  "revision_id": "298172"
 }, 
 {
  "author": "mturk", 
  "date": "2002-11-22T18:56:45.000000Z", 
  "msg": [
   "Add the description for JVM startup argument for TC 5.0", 
   "The accepted argument is 'startd' for Bootstrap class.", 
   "That way it will behave like a daemon."
  ], 
  "revision_id": "298171"
 }, 
 {
  "author": "mturk", 
  "date": "2002-11-22T17:46:33.000000Z", 
  "msg": [
   "1. Setting port to 0 will disble the channel socket. This is usefull for JNI", 
   "where there is no need for channelSocket. Less wasted resources...", 
   "2. Allow address=\"x.x.x.x\" in the server.xml. This wil bind the specified", 
   "IP address in case one have few on the box."
  ], 
  "revision_id": "298170"
 }
]