[
 {
  "author": "remm", 
  "date": "2005-03-07T13:26:59.000000Z", 
  "msg": [
   "- private -> protected."
  ], 
  "revision_id": "300334"
 }, 
 {
  "author": "remm", 
  "date": "2005-03-04T15:33:41.000000Z", 
  "msg": [
   "- Cleanup.", 
   "- Remove special root and global loggers handling (it seems useless to me). global will simply delegate, so that it will always use the JVM configuration.", 
   "- Remove some if(securityManager), which is only really useful in the critical path (the methods concerned were already synchromized, so ...)."
  ], 
  "revision_id": "300333"
 }, 
 {
  "author": "remm", 
  "date": "2005-03-04T14:59:19.000000Z", 
  "msg": [
   "- Fix NPEs when context CL is null, which occurs in JNI mode (cool feature ...)."
  ], 
  "revision_id": "300332"
 }, 
 {
  "author": "remm", 
  "date": "2005-03-03T18:29:45.000000Z", 
  "msg": [
   "- Remove FIXME."
  ], 
  "revision_id": "300331"
 }, 
 {
  "author": "remm", 
  "date": "2005-03-03T13:34:17.000000Z", 
  "msg": [
   "- Add a sample default configuration. Webapps can use their own configuration by having a logging.properties in their own classloader.", 
   "- Properly parse and set handlers.", 
   "- Fix useParentHandlers initialization (it tended to be always set to false).", 
   "- The necessary system property is not present yet, however (-Djava.util.logging.manager=org.apache.juli.ClassLoaderLogManager is needed", 
   "in JAVA_OPTS or CATALINA_OPTS). Some hacking of the startup scripts is needed."
  ], 
  "revision_id": "300330"
 }
]