[
 {
  "author": "sboag", 
  "date": "2000-12-14T18:37:42.000000Z", 
  "msg": [
   "Replaced TFactoryConfigurationException with TransformerConfigurationException.", 
   "Sorry, this broke the build last night."
  ], 
  "revision_id": "333969"
 }, 
 {
  "author": "mmidy", 
  "date": "2000-12-14T16:57:27.000000Z", 
  "msg": [
   "Javadoc updates"
  ], 
  "revision_id": "333968"
 }, 
 {
  "author": "jkesselm", 
  "date": "2000-12-14T16:06:13.000000Z", 
  "msg": [
   "Docs"
  ], 
  "revision_id": "333967"
 }, 
 {
  "author": "sboag", 
  "date": "2000-12-14T00:19:26.000000Z", 
  "msg": [
   "Changes for TrAX as per JCP process:", 
   "TransformerHandler now implements DTDHandler.", 
   "TransformerConfigurationException now has SourceLocator constructors.", 
   "TransformerException now has setLocator.", 
   "Nested exceptions changed to Throwable, in order to support getCause.", 
   "TFactoryConfigurationError changed to TransformerFactoryConfigurationError.", 
   "The way output properties nest has been respecified (javadoc change).", 
   "Many javadoc editorial changes."
  ], 
  "revision_id": "333966"
 }, 
 {
  "author": "mmidy", 
  "date": "2000-12-13T22:59:42.000000Z", 
  "msg": [
   "Javadoc updates"
  ], 
  "revision_id": "333965"
 }
]