[
 {
  "author": "avik", 
  "date": "2003-07-31T19:01:47.000000Z", 
  "msg": [
   "bug 19961, John Lloyd"
  ], 
  "revision_id": "353274"
 }, 
 {
  "author": "avik", 
  "date": "2003-07-31T17:55:36.000000Z", 
  "msg": [
   "apply to head: bug id 21674: Javadoc changes. Submitted by Eric Ladner. Thanks"
  ], 
  "revision_id": "353273"
 }, 
 {
  "author": "avik", 
  "date": "2003-07-31T17:55:09.000000Z", 
  "msg": [
   "bug id 21674: Javadoc changes. Submitted by Eric Ladner. Thanks"
  ], 
  "revision_id": "353272"
 }, 
 {
  "author": "tetsuya", 
  "date": "2003-07-29T10:40:19.000000Z", 
  "msg": [
   "FIXED miscs (mail.html --> mail2.html etc)"
  ], 
  "revision_id": "353271"
 }, 
 {
  "author": "tetsuya", 
  "date": "2003-07-29T10:26:33.000000Z", 
  "msg": [
   "Comment out: CVS Changelog"
  ], 
  "revision_id": "353270"
 }
]