[
 {
  "author": "nick", 
  "date": "2005-09-05T09:34:07.000000Z", 
  "msg": [
   "List Yegor as co-author on file, since his information on Font and Text", 
   "Styling is now included"
  ], 
  "revision_id": "353784"
 }, 
 {
  "author": "nick", 
  "date": "2005-09-04T20:09:11.000000Z", 
  "msg": [
   "NCB: Updated documentation on StyleTextPropAtom"
  ], 
  "revision_id": "353783"
 }, 
 {
  "author": "nick", 
  "date": "2005-09-04T19:26:40.000000Z", 
  "msg": [
   "Finish off character style tests, and add paragraph style tests"
  ], 
  "revision_id": "353782"
 }, 
 {
  "author": "nick", 
  "date": "2005-09-04T19:25:02.000000Z", 
  "msg": [
   "Handle internal representation duplication correctly"
  ], 
  "revision_id": "353781"
 }, 
 {
  "author": "jheight", 
  "date": "2005-09-02T03:50:24.000000Z", 
  "msg": [
   "BitfieldFactory update"
  ], 
  "revision_id": "353780"
 }
]