[
 {
  "author": "cschoett", 
  "date": "2006-01-20T21:08:39.892210Z", 
  "msg": [
   "Resolution for BEEHIVE-1014.", 
   "*) Reverted generated control file veloctiy templates back to using import statements.", 
   "*) Added eclipse annotation 'SuppressWarnings(\"all\")' to each of the generated classes.", 
   "*) Added serialVersionUID value to each of the generated classes which are serializable.", 
   "DRTs: all beehive passed", 
   "The net effect will be that there will no longer be warnings displayed for these generated classes in eclipse."
  ], 
  "revision_id": "370899"
 }, 
 {
  "author": "dennisl", 
  "date": "2006-01-20T20:56:46.873790Z", 
  "msg": [
   "Fix broken and redirected links."
  ], 
  "revision_id": "370898"
 }, 
 {
  "author": "hstern", 
  "date": "2006-01-20T20:19:19.993743Z", 
  "msg": [
   "* rules/70_uribl.cf", 
   "* rulesrc/core/25_uribl2.cf: Moved testing rules to 25_uribl2.cf", 
   "* rulesrc/core/50_scores.cf: Added scores for new URIBL rules.", 
   "black=3.0", 
   "grey=1.0", 
   "red=0"
  ], 
  "revision_id": "370897"
 }, 
 {
  "author": "slive", 
  "date": "2006-01-20T20:00:50.457371Z", 
  "msg": [
   "Regular mirror updates."
  ], 
  "revision_id": "370896"
 }, 
 {
  "author": "thorsten", 
  "date": "2006-01-20T19:58:47.803188Z", 
  "msg": [
   "minor docu change"
  ], 
  "revision_id": "370895"
 }
]