[
 {
  "author": "bayard", 
  "date": "2006-06-25T20:18:19.027567Z", 
  "msg": [
   "Removing cvs2svn migration flotsam"
  ], 
  "revision_id": "417060"
 }, 
 {
  "author": "bayard", 
  "date": "2006-06-25T20:18:05.471430Z", 
  "msg": [
   "Removing cvs2svn migration flotsam"
  ], 
  "revision_id": "417059"
 }, 
 {
  "author": "bayard", 
  "date": "2006-06-25T20:17:49.747826Z", 
  "msg": [
   "Removing cvs2svn migration flotsam"
  ], 
  "revision_id": "417058"
 }, 
 {
  "author": "bayard", 
  "date": "2006-06-25T20:17:41.858882Z", 
  "msg": [
   "Removing cvs2svn migration flotsam"
  ], 
  "revision_id": "417057"
 }, 
 {
  "author": "bayard", 
  "date": "2006-06-25T20:17:34.521770Z", 
  "msg": [
   "Removing cvs2svn migration flotsam"
  ], 
  "revision_id": "417056"
 }
]