[
 {
  "author": "jta", 
  "date": "2006-08-29T23:29:27.411891Z", 
  "msg": [
   "DERBY-1575 Update Reference Guide to document full syntax of CASE expression.", 
   "Committed patch DERBY-1575_fix.diff by Kim Haase <camilla.haase@sun.com>."
  ], 
  "revision_id": "438290"
 }, 
 {
  "author": "fuzzylogic", 
  "date": "2006-08-29T23:26:32.297580Z", 
  "msg": [
   "Fix location of test directory in the -lib distribution."
  ], 
  "revision_id": "438289"
 }, 
 {
  "author": "elecharny", 
  "date": "2006-08-29T23:25:08.843216Z", 
  "msg": [
   "Added a check for requestName : invalid OIDs were allowed."
  ], 
  "revision_id": "438288"
 }, 
 {
  "author": "sichen", 
  "date": "2006-08-29T23:19:23.051674Z", 
  "msg": [
   "Show marketing package atp/qoh from components during order entry if the product is a marketing package"
  ], 
  "revision_id": "438287"
 }, 
 {
  "author": "sichen", 
  "date": "2006-08-29T23:19:16.233697Z", 
  "msg": [
   "Turned off transactions for all the getInventory_ services -- they do not store anything and should not require them.  Also added marketing package ATP/QOH to the getProductInventorySummaryForItems service which searches across all facilities"
  ], 
  "revision_id": "438286"
 }
]