[
 {
  "author": "gawor", 
  "date": "2007-04-18T04:06:29.500167Z", 
  "msg": [
   "workaround for jetty character encoding problems"
  ], 
  "revision_id": "529850"
 }, 
 {
  "author": "ningjiang", 
  "date": "2007-04-18T03:54:15.594579Z", 
  "msg": [
   "Fixed soap bindings test's build error"
  ], 
  "revision_id": "529849"
 }, 
 {
  "author": "dos", 
  "date": "2007-04-18T03:40:28.690813Z", 
  "msg": [
   "first whack at generating scores for newly promoted rules... fix scores for the rules from the base release, let the garescorer assign scores to the new rules based on the last 2 months of mail appearing in the nightly mass-check logs"
  ], 
  "revision_id": "529848"
 }, 
 {
  "author": "trustin", 
  "date": "2007-04-18T03:32:20.054084Z", 
  "msg": [
   "Fixed DIRMINA-279 (CompressionFilter returns error -5 (Z_BUF_ERROR) from jzlib in MINA 1.0 but not in MINA 0.9.4)", 
   "* Found my previous fix doesn't work if the compression filter is the first filter in the chain."
  ], 
  "revision_id": "529847"
 }, 
 {
  "author": "trustin", 
  "date": "2007-04-18T03:32:15.914522Z", 
  "msg": [
   "Fixed DIRMINA-279 (CompressionFilter returns error -5 (Z_BUF_ERROR) from jzlib in MINA 1.0 but not in MINA 0.9.4)", 
   "* Found my previous fix doesn't work if the compression filter is the first filter in the chain."
  ], 
  "revision_id": "529846"
 }
]