[
 {
  "author": "kahatlen", 
  "date": "2007-05-21T14:11:03.496834Z", 
  "msg": [
   "DERBY-2674 (partial) Stop running jdbc40 tests in the old test framework", 
   "The attached patch removes the TestPreparedStatementMethods test and", 
   "associated files that are not used by other tests.", 
   "An inspection of PreparedStatementTest showed that testing of", 
   "isPoolable/setPoolable on a closed PreparedStatement was omitted when", 
   "the test was ported to Junit. The patch adds test cases for this to", 
   "PreparedStatementTest.", 
   "Contributed by \u00d8ystein Gr\u00f8vlen."
  ], 
  "revision_id": "540150"
 }, 
 {
  "author": "fhanik", 
  "date": "2007-05-21T14:08:04.664662Z", 
  "msg": [
   "forward port"
  ], 
  "revision_id": "540149"
 }, 
 {
  "author": "evenisse", 
  "date": "2007-05-21T14:03:35.532527Z", 
  "msg": [
   "[MRELEASE-177] Fix generateReleasePoms phase.", 
   "Submitted by: Mark Hobson"
  ], 
  "revision_id": "540148"
 }, 
 {
  "author": "mrdon", 
  "date": "2007-05-21T13:55:34.607674Z", 
  "msg": [
   "Improving javadocs", 
   "WW-1939"
  ], 
  "revision_id": "540147"
 }, 
 {
  "author": "mrdon", 
  "date": "2007-05-21T13:54:32.606581Z", 
  "msg": [
   "Improving javadoc", 
   "WW-1939"
  ], 
  "revision_id": "540146"
 }
]