[
 {
  "author": "carnold", 
  "date": "2007-06-04T19:59:13.747839Z", 
  "msg": [
   "Moving log4j compansions out of sandbox"
  ], 
  "revision_id": "544230"
 }, 
 {
  "author": "wrowe", 
  "date": "2007-06-04T19:58:36.953438Z", 
  "msg": [
   "Notes"
  ], 
  "revision_id": "544229"
 }, 
 {
  "author": "wrowe", 
  "date": "2007-06-04T19:58:22.246984Z", 
  "msg": [
   "Notes"
  ], 
  "revision_id": "544228"
 }, 
 {
  "author": "wrowe", 
  "date": "2007-06-04T19:58:06.903385Z", 
  "msg": [
   "Notes"
  ], 
  "revision_id": "544227"
 }, 
 {
  "author": "nbubna", 
  "date": "2007-06-04T19:58:03.016770Z", 
  "msg": [
   "make valid/invalid scope annotations inherited"
  ], 
  "revision_id": "544226"
 }
]