[
 {
  "author": "svkrish", 
  "date": "2007-09-18T05:38:29.049201Z", 
  "msg": [
   "applying patch subitted in https://issues.apache.org/jira/browse/TUSCANY-1730"
  ], 
  "revision_id": "576710"
 }, 
 {
  "author": "jsdelfino", 
  "date": "2007-09-18T05:38:16.359665Z", 
  "msg": [
   "Fix for TUSCANY-1731. Excluded xerces from axiom-api dependencies, and replaced by a dependency on xerces 2.8.1. Added a dependency on xml-api 1.3.03 instead to have this level instead of 1.0.b2. This fixes NoSuchMethodError and VerifyError exceptions when running on WebSphere."
  ], 
  "revision_id": "576709"
 }, 
 {
  "author": "svkrish", 
  "date": "2007-09-18T05:37:11.065954Z", 
  "msg": [
   "applying patch submitted for https://issues.apache.org/jira/browse/TUSCANY-1730"
  ], 
  "revision_id": "576708"
 }, 
 {
  "author": "woonsan", 
  "date": "2007-09-18T05:35:28.762452Z", 
  "msg": [
   "[JS2-634] edit_defaults custom portlet mode", 
   "Implemented edit_defaults and about custom portlet modes.", 
   "Only admin users can use edit_defaults mode, and the default preferences are stored in PSML pages.", 
   "To enable this feature, the portlet decoration properties should have 'actions.factory=CustomDecoratorActionsAdapter'. See /decorations/portlet/tigris/decorator.properties.", 
   "Implemented edit_defaults and about custom portlet modes for the PickANumber portlet."
  ], 
  "revision_id": "576707"
 }, 
 {
  "author": "svkrish", 
  "date": "2007-09-18T05:29:37.017346Z", 
  "msg": [
   "applying patch subitted in https://issues.apache.org/jira/browse/TUSCANY-1729"
  ], 
  "revision_id": "576706"
 }
]