[
 {
  "author": "dos", 
  "date": "2007-10-29T23:49:37.779643Z", 
  "msg": [
   "updated scores for revision 589545 active rules added since last mass-check"
  ], 
  "revision_id": "589915"
 }, 
 {
  "author": "brett", 
  "date": "2007-10-29T23:48:54.905914Z", 
  "msg": [
   "remove test that no longer exists"
  ], 
  "revision_id": "589914"
 }, 
 {
  "author": "sebor", 
  "date": "2007-10-29T23:41:53.560112Z", 
  "msg": [
   "2007-10-29  Martin Sebor  <sebor@roguewave.com>", 
   "Merged rev 589912 (fix for STDCXX-624) from branches/4.2.x.", 
   "* NO_INT_TRAPS.cpp (main): Worked even harder to foil optimizers", 
   "and trigger a trap (such as SIGFPE) for integer arithmetic."
  ], 
  "revision_id": "589913"
 }, 
 {
  "author": "sebor", 
  "date": "2007-10-29T23:40:50.627433Z", 
  "msg": [
   "2007-10-29  Martin Sebor  <sebor@roguewave.com>", 
   "STDCXX-624", 
   "* etc/config/src/NO_INT_TRAPS.cpp (main): Worked even harder to foil", 
   "optimizers and trigger a trap (such as SIGFPE) for integer arithmetic."
  ], 
  "revision_id": "589912"
 }, 
 {
  "author": "trawick", 
  "date": "2007-10-29T23:36:09.049054Z", 
  "msg": [
   "when !APR_HAS_RANDOM, use a lame initial \"random\" number", 
   "in test programs instead of bombing with a link failure"
  ], 
  "revision_id": "589911"
 }
]