[
 {
  "author": "dblevins", 
  "date": "2007-12-13T20:00:04.881208Z", 
  "msg": [
   "svn propset 'svn:ignore'"
  ], 
  "revision_id": "604010"
 }, 
 {
  "author": "wrowe", 
  "date": "2007-12-13T19:58:37.454012Z", 
  "msg": [
   "Top level projects don't require this disclaimer.  Congratulations!"
  ], 
  "revision_id": "604009"
 }, 
 {
  "author": "jleroux", 
  "date": "2007-12-13T19:57:11.770632Z", 
  "msg": [
   "Applied fix from trunk for revision: 602997"
  ], 
  "revision_id": "604008"
 }, 
 {
  "author": "jleroux", 
  "date": "2007-12-13T19:56:30.535445Z", 
  "msg": [
   "Applied fix from trunk for revision: 602859"
  ], 
  "revision_id": "604007"
 }, 
 {
  "author": "dkulp", 
  "date": "2007-12-13T19:51:19.036251Z", 
  "msg": [
   "Merge part of r603819"
  ], 
  "revision_id": "604006"
 }
]