[
 {
  "author": "bdelacretaz", 
  "date": "2008-02-13T15:28:27.699971Z", 
  "msg": [
   "moved my blog"
  ], 
  "revision_id": "627470"
 }, 
 {
  "author": "olegk", 
  "date": "2008-02-13T15:28:26.992713Z", 
  "msg": [
   "Added dependencies section to the README file"
  ], 
  "revision_id": "627469"
 }, 
 {
  "author": "schor", 
  "date": "2008-02-13T15:27:50.483522Z", 
  "msg": [
   "[UIMA-709] Change assembly to just copy the plugins into where they go in the distr.  \"zip\" files for these are no longer produced; no unpacking is needed."
  ], 
  "revision_id": "627468"
 }, 
 {
  "author": "olegk", 
  "date": "2008-02-13T15:27:47.737333Z", 
  "msg": [
   "Added dependencies section to the README file"
  ], 
  "revision_id": "627467"
 }, 
 {
  "author": "kahatlen", 
  "date": "2008-02-13T15:25:22.361679Z", 
  "msg": [
   "DERBY-2128: The word 'class' appears twice for the message SIF01.V"
  ], 
  "revision_id": "627466"
 }
]