[
 {
  "author": "rfrovarp", 
  "date": "2008-03-11T19:24:44.452695Z", 
  "msg": [
   "Fix missing version number from classpath"
  ], 
  "revision_id": "636070"
 }, 
 {
  "author": "olegk", 
  "date": "2008-03-11T19:17:17.456751Z", 
  "msg": [
   "Added the most fundamental test cases for throttling protocol handlers"
  ], 
  "revision_id": "636069"
 }, 
 {
  "author": "svkrish", 
  "date": "2008-03-11T19:16:42.458992Z", 
  "msg": [
   "fixes related to targetnamespace and fixes cascading out of some cleanup of policy support for operations"
  ], 
  "revision_id": "636068"
 }, 
 {
  "author": "rajdavies", 
  "date": "2008-03-11T19:13:50.680527Z", 
  "msg": [
   "make lazy dispatch the default for queues"
  ], 
  "revision_id": "636067"
 }, 
 {
  "author": "olegk", 
  "date": "2008-03-11T19:12:55.822042Z", 
  "msg": [
   "Fixed bug in NHttpEntityWrapper causing infinite loop in the async protocol handlers"
  ], 
  "revision_id": "636066"
 }
]