[
 {
  "author": "thorsten", 
  "date": "2008-03-19T20:34:15.709379Z", 
  "msg": [
   "LABS-117 Replace all linkedHashmaps within the factory classes with cocoons configurator:bean-map"
  ], 
  "revision_id": "639000"
 }, 
 {
  "author": "jacopoc", 
  "date": "2008-03-19T20:29:25.026486Z", 
  "msg": [
   "Added information about allScreenInfosReferringToEntityName; thanks to David Jones for the help."
  ], 
  "revision_id": "638999"
 }, 
 {
  "author": "niallp", 
  "date": "2008-03-19T20:27:16.807762Z", 
  "msg": [
   "Try to fix gump failure"
  ], 
  "revision_id": "638998"
 }, 
 {
  "author": "bentmann", 
  "date": "2008-03-19T20:26:43.801372Z", 
  "msg": [
   "o Added link to article about Maven's class loading"
  ], 
  "revision_id": "638997"
 }, 
 {
  "author": "gbayon", 
  "date": "2008-03-19T20:15:15.215066Z", 
  "msg": [
   "rename directory"
  ], 
  "revision_id": "638996"
 }
]