[
 {
  "author": "lu4242", 
  "date": "2008-09-11T21:24:30.161384Z", 
  "msg": [
   "update modelId to new artifacts names"
  ], 
  "revision_id": "694490"
 }, 
 {
  "author": "lu4242", 
  "date": "2008-09-11T21:24:20.546674Z", 
  "msg": [
   "update modelId to new artifacts names"
  ], 
  "revision_id": "694489"
 }, 
 {
  "author": "rgardler", 
  "date": "2008-09-11T21:18:48.958540Z", 
  "msg": [
   "reverting r691518 as it broke sites pulling wiki content from live servers rather than using local files"
  ], 
  "revision_id": "694488"
 }, 
 {
  "author": "dkulp", 
  "date": "2008-09-11T21:17:48.863157Z", 
  "msg": [
   "Merged revisions 694466 via svnmerge from", 
   "https://svn.apache.org/repos/asf/cxf/branches/2.1.x-fixes", 
   "................", 
   "r694466 | dkulp | 2008-09-11 16:39:32 -0400 (Thu, 11 Sep 2008) | 9 lines", 
   "Merged revisions 693653 via svnmerge from", 
   "https://svn.apache.org/repos/asf/cxf/trunk", 
   "........", 
   "r693653 | ericjohnson | 2008-09-09 19:08:23 -0400 (Tue, 09 Sep 2008) | 1 line", 
   "added comments clarifying the use of the attributes", 
   "........", 
   "................"
  ], 
  "revision_id": "694487"
 }, 
 {
  "author": "olamy", 
  "date": "2008-09-11T21:12:02.136983Z", 
  "msg": [
   "update release note content with two new issues", 
   "add links in the home page (wiki in cwiki and blog)"
  ], 
  "revision_id": "694486"
 }
]