[
 {
  "author": "rdonkin", 
  "date": "2009-05-07T20:54:28.377336Z", 
  "msg": [
   "Fixed ordering bug in EXPUNGE. IMAP-78 https://issues.apache.org/jira/browse/IMAP-78"
  ], 
  "revision_id": "772770"
 }, 
 {
  "author": "radup", 
  "date": "2009-05-07T20:52:07.510900Z", 
  "msg": [
   "Made XmlValueRef constructor public."
  ], 
  "revision_id": "772769"
 }, 
 {
  "author": "pgier", 
  "date": "2009-05-07T20:49:18.614368Z", 
  "msg": [
   "[MANTTASKS-147] Preserve original behaviour of useScope and add new scope option."
  ], 
  "revision_id": "772768"
 }, 
 {
  "author": "radup", 
  "date": "2009-05-07T20:47:50.096038Z", 
  "msg": [
   "Removed an unnecessary cast from the generated code. Contributed by Wesley Leggette."
  ], 
  "revision_id": "772767"
 }, 
 {
  "author": "tabish", 
  "date": "2009-05-07T20:41:40.718137Z", 
  "msg": [
   "AMQCPP-242 Changes to try and make AtomicInteger actually perform its operations atomically."
  ], 
  "revision_id": "772766"
 }
]