[
 {
  "author": "rickhall", 
  "date": "2009-08-04T20:50:59.179494Z", 
  "msg": [
   "Remove unnecessary directories."
  ], 
  "revision_id": "800965"
 }, 
 {
  "author": "tvolkert", 
  "date": "2009-08-04T20:49:44.681768Z", 
  "msg": [
   "Fix small bug in QueryServlet related to fix to PIVOT-172"
  ], 
  "revision_id": "800964"
 }, 
 {
  "author": "olga", 
  "date": "2009-08-04T20:49:11.971931Z", 
  "msg": [
   "update to svn external due to hadoop project split"
  ], 
  "revision_id": "800963"
 }, 
 {
  "author": "wrowe", 
  "date": "2009-08-04T20:48:56.000753Z", 
  "msg": [
   "and we are at util .10-dev"
  ], 
  "revision_id": "800962"
 }, 
 {
  "author": "francisdb", 
  "date": "2009-08-04T20:48:34.472137Z", 
  "msg": [
   "add rat excludes"
  ], 
  "revision_id": "800961"
 }
]