[
 {
  "author": "mturk", 
  "date": "2009-10-23T08:15:02.656539Z", 
  "msg": [
   "We don't have File instance any more"
  ], 
  "revision_id": "828955"
 }, 
 {
  "author": "dejanb", 
  "date": "2009-10-23T08:11:17.703867Z", 
  "msg": [
   "test for http://issues.apache.org/activemq/browse/AMQ-1873 - stomp toon many open files"
  ], 
  "revision_id": "828954"
 }, 
 {
  "author": "mturk", 
  "date": "2009-10-23T08:10:04.908907Z", 
  "msg": [
   "Second stage of decoupling File from java.io.File. File now only provide static methods"
  ], 
  "revision_id": "828953"
 }, 
 {
  "author": "norman", 
  "date": "2009-10-23T07:44:40.877898Z", 
  "msg": [
   "We need a marker interface to tell the PhoenixLoader to not try to inject resources again.. to many workarounds..."
  ], 
  "revision_id": "828952"
 }, 
 {
  "author": "vamsic007", 
  "date": "2009-10-23T07:41:37.684852Z", 
  "msg": [
   "Make the WebImplementationProcessor compute the injection points for properties, references and resources like component context etc."
  ], 
  "revision_id": "828951"
 }
]