[
 {
  "author": "josander", 
  "date": "2004-09-21T14:31:06.641873Z", 
  "msg": [
   "* STATUS", 
   "nominate r10978 as candidate for 1.1.x"
  ], 
  "revision_id": "851135"
 }, 
 {
  "author": "jaa", 
  "date": "2004-09-21T02:22:10.621447Z", 
  "msg": [
   "Added a new entry, '#def-wedged-repository' which tries to explain what", 
   "we mean when we say that a repository is wedged.", 
   "* www/project_faq.html", 
   "(def-wedged-repository): ditto."
  ], 
  "revision_id": "851134"
 }, 
 {
  "author": "cmpilato", 
  "date": "2004-09-20T22:17:50.810995Z", 
  "msg": [
   "Expose the svn_repos_trace_node_locations() functionality through the", 
   "Python bindings.", 
   "* subversion/bindings/swig/python/libsvn_swig_py/swigutil_py.h", 
   "* subversion/bindings/swig/python/libsvn_swig_py/swigutil_py.c", 
   "(svn_swig_py_locationhash_to_dict, svn_swig_py_revnums_to_array): New.", 
   "* subversion/bindings/swig/svn_repos.i", 
   "Swigify the 'location_revisions' input, and 'locations' output, of", 
   "svn_repos_trace_node_locations()."
  ], 
  "revision_id": "851133"
 }, 
 {
  "author": "cmpilato", 
  "date": "2004-09-20T22:14:48.892699Z", 
  "msg": [
   "Fix a little typo."
  ], 
  "revision_id": "851132"
 }, 
 {
  "author": "kfogel", 
  "date": "2004-09-20T20:13:08.589162Z", 
  "msg": [
   "Doc tweaks.", 
   "Suggested by: Grzegorz Adam Hankiewicz <gradha@titanium.sabren.com>", 
   "* HACKING", 
   "(Patch submission guidelines): Revise attachment policy, to match", 
   "current consensus and www/mailing-list-guidelines.html.", 
   "(Writing log messages): Clarify need for consistency."
  ], 
  "revision_id": "851131"
 }
]