[
 {
  "author": "wrowe", 
  "date": "2000-09-25T19:03:11.000000Z", 
  "msg": [
   "Cleaner feature tests and new -d -m -s -p options for crypt, MD5, SHA1", 
   "and plaintext password cyphers.  Not certain what the $^O tag for", 
   "NETWARE really is, so this may need to be fixed.", 
   "PR:", 
   "Obtained from:", 
   "Submitted by:", 
   "Reviewed by:"
  ], 
  "revision_id": "86319"
 }, 
 {
  "author": "dirkx", 
  "date": "2000-09-25T18:55:44.000000Z", 
  "msg": [
   "New covalent products"
  ], 
  "revision_id": "86318"
 }, 
 {
  "author": "stoddard", 
  "date": "2000-09-25T16:42:49.000000Z", 
  "msg": [
   "Fix compile break. It should be apr_pstrcat."
  ], 
  "revision_id": "86317"
 }, 
 {
  "author": "mjc", 
  "date": "2000-09-25T14:36:06.000000Z", 
  "msg": [
   "Fix the URL"
  ], 
  "revision_id": "86316"
 }, 
 {
  "author": "mjc", 
  "date": "2000-09-25T14:29:33.000000Z", 
  "msg": [
   "Change org"
  ], 
  "revision_id": "86315"
 }
]