[
 {
  "author": "crossley", 
  "date": "2009-11-20T08:59:56.110968Z", 
  "msg": [
   "Fix typo. (Treat words carefully. Do not tempt such things. :-)"
  ], 
  "revision_id": "882455"
 }, 
 {
  "author": "ashish", 
  "date": "2009-11-20T08:59:05.701291Z", 
  "msg": [
   "Applied patch from jira issue OFBIZ-3208 - On order view page when clicking on \"Create As New Order\", the adjustments Shipping and Handling and Sales Tax are duplicated.", 
   "Patch will resolve the following Issues", 
   "1) Shipping and Handling Charges are added twice in new order amount.", 
   "2) Sales Tax are added twice in new order amount.", 
   "3) Add extra tax on shipping and handling charges for new order.", 
   "4) When click on \"Create as New Order\" Link, it is Giving NPE on some Promotion (Happy Hour", 
   "Promotion 9020).", 
   "5) Click on \"Edit Items\" Link and then \"Update\" Link it is it is Giving NPE on some Promotion (Happy", 
   "Hour Promotion 9020).", 
   "Thanks Arpit for the contribution."
  ], 
  "revision_id": "882454"
 }, 
 {
  "author": "olamy", 
  "date": "2009-11-20T08:55:01.829941Z", 
  "msg": [
   "use maven-plugin-testing-harness released version"
  ], 
  "revision_id": "882453"
 }, 
 {
  "author": "jleroux", 
  "date": "2009-11-20T08:52:53.566144Z", 
  "msg": [
   "A patch from Sharan Foga \"Special feature to allow submitting patches for online help update\" (https://issues.apache.org/jira/browse/OFBIZ-2219) - OFBIZ-2219", 
   "Frmatting and tidy up using the itemized and orderedlist docbook commands for Tax Authorities. I've also included some documentation on the Bank Reconciliation process."
  ], 
  "revision_id": "882452"
 }, 
 {
  "author": "jm", 
  "date": "2009-11-20T08:50:55.549745Z", 
  "msg": [
   "promotions validated"
  ], 
  "revision_id": "882451"
 }
]