[
 {
  "author": "yegor", 
  "date": "2009-12-25T15:15:55.123767Z", 
  "msg": [
   "added HSSF usermodel tests for array formulas, added support for array formulas in ss interfaces"
  ], 
  "revision_id": "893870"
 }, 
 {
  "author": "yegor", 
  "date": "2009-12-25T15:13:26.243069Z", 
  "msg": [
   "fixed incorrect initialization of --noheader option in BiffViewer"
  ], 
  "revision_id": "893869"
 }, 
 {
  "author": "ningjiang", 
  "date": "2009-12-25T14:54:09.783881Z", 
  "msg": [
   "CAMEL-2322 Updated the import version of the spring packages"
  ], 
  "revision_id": "893868"
 }, 
 {
  "author": "ningjiang", 
  "date": "2009-12-25T14:53:44.448692Z", 
  "msg": [
   "CAMEL-2322 Updated the import version of the spring packages"
  ], 
  "revision_id": "893867"
 }, 
 {
  "author": "gpetracek", 
  "date": "2009-12-25T14:40:53.675140Z", 
  "msg": [
   "EXTVAL-79 initial implementation"
  ], 
  "revision_id": "893866"
 }
]