[
 {
  "author": "zshao", 
  "date": "2010-02-05T21:25:54.621515Z", 
  "msg": [
   "HIVE-1120. In ivy offline mode, don't delete downloaded jars. (John Sichi via zshao)"
  ], 
  "revision_id": "907100"
 }, 
 {
  "author": "mbenson", 
  "date": "2010-02-05T21:22:29.039493Z", 
  "msg": [
   "clean up toClass(Object[]) test"
  ], 
  "revision_id": "907099"
 }, 
 {
  "author": "dwoods", 
  "date": "2010-02-05T21:21:19.735405Z", 
  "msg": [
   "added 2.1.3-beta and 2.1.3-beta-SNAPSHOT versions"
  ], 
  "revision_id": "907098"
 }, 
 {
  "author": "rhillegas", 
  "date": "2010-02-05T21:19:23.706899Z", 
  "msg": [
   "DERBY-651: Make it possible to have UDT columns in table functions."
  ], 
  "revision_id": "907097"
 }, 
 {
  "author": "scottbw", 
  "date": "2010-02-05T21:16:14.064861Z", 
  "msg": [
   "Changed the behaviour of preferences such that a request for a non-existing preference returns undefined instead of null; also calling clear or removeItem on a preference deletes it rather than setting it to null. This enables us to pass the \"au\" conformance test for W3C Widgets: Widget Interface (see http://dev.w3.org/2006/waf/widgets-api/test-suite/)"
  ], 
  "revision_id": "907096"
 }
]