[
 {
  "author": "ehu", 
  "date": "2010-08-30T08:40:45.325718Z", 
  "msg": [
   "Change query for consistency.", 
   "* subversion/libsvn_wc/wc-queries.sql", 
   "(STMT_UPDATE_NODE_WORKING_EXCLUDED): Use LIMITed nested query,", 
   "just as STMT_UPDATE_NODE_WORKING_PRESENCE does."
  ], 
  "revision_id": "990730"
 }, 
 {
  "author": "stsp", 
  "date": "2010-08-30T08:38:39.495935Z", 
  "msg": [
   "* subversion/libsvn_client/patch.c", 
   "(install_patched_prop_targets): In r987735, I suggested skipping targets", 
   "which are trying to patch invalid properties (e.g. create svn:executable", 
   "on a directory). A better approach would be to reject any offending", 
   "property hunks, but apply the rest. Update my comment to that effect."
  ], 
  "revision_id": "990729"
 }, 
 {
  "author": "jacopoc", 
  "date": "2010-08-30T08:26:41.311858Z", 
  "msg": [
   "Backported rev. 990726: \"Fixed a fop runtime error happening when no materials or no tasks were defined.\""
  ], 
  "revision_id": "990728"
 }, 
 {
  "author": "struberg", 
  "date": "2010-08-30T08:25:07.474646Z", 
  "msg": [
   "add non-standard OWB behaviour description"
  ], 
  "revision_id": "990727"
 }, 
 {
  "author": "jacopoc", 
  "date": "2010-08-30T08:24:10.669391Z", 
  "msg": [
   "Fixed a fop runtime error happening when no materials or no tasks were defined."
  ], 
  "revision_id": "990726"
 }
]